{"file:///f%3A/Project/packet/receiveFrame.h":{"language":"C++","code":41,"comment":5,"blank":5},"file:///f%3A/Project/packet/receivePacket.c":{"language":"C","code":47,"comment":0,"blank":2},"file:///f%3A/Project/packet/receivePacket.h":{"language":"C++","code":6,"comment":0,"blank":3},"file:///f%3A/Project/packet/changeType.c":{"language":"C","code":37,"comment":0,"blank":7},"file:///f%3A/Project/packet/sendFrame.c":{"language":"C","code":0,"comment":0,"blank":1},"file:///f%3A/Project/packet/receiveFrame.c":{"language":"C","code":194,"comment":3,"blank":26},"file:///f%3A/Project/packet/changeType.h":{"language":"C++","code":4,"comment":0,"blank":3},"file:///f%3A/Project/packet/sendFrame.h":{"language":"C++","code":0,"comment":0,"blank":1},"file:///f%3A/Project/packet/sendPacket.c":{"language":"C","code":48,"comment":0,"blank":1},"file:///f%3A/Project/packet/sendPacket.h":{"language":"C++","code":6,"comment":0,"blank":3}}